nanome_vault/AESCipher.py
nanome_vault/Vault.py
nanome_vault/VaultManager.py
nanome_vault/VaultServer.py
nanome_vault/Workspace.py
nanome_vault/__init__.py
nanome_vault/WebUI/dist/favicon.ico
nanome_vault/WebUI/dist/index.html
nanome_vault/WebUI/dist/css/app.4d3d21f3.css
nanome_vault/WebUI/dist/img/logo.4d600d0e.png
nanome_vault/WebUI/dist/js/app.b64c3857.js
nanome_vault/WebUI/dist/js/chunk-vendors.4311c6ec.js
nanome_vault/menus/VaultMenu.py
nanome_vault/menus/__init__.py
nanome_vault/menus/icons/lock.png
nanome_vault/menus/icons/up.png
nanome_vault/menus/json/list_item.json
nanome_vault/menus/json/menu.json
nanome_vault-2.2.2.dist-info/LICENSE
nanome_vault-2.2.2.dist-info/METADATA
nanome_vault-2.2.2.dist-info/WHEEL
nanome_vault-2.2.2.dist-info/entry_points.txt
nanome_vault-2.2.2.dist-info/top_level.txt
nanome_vault-2.2.2.dist-info/RECORD
