Metadata-Version: 2.1
Name: nanome-vault
Version: 2.2.2
Summary: A Nanome plugin that creates a web interface to upload files and make them available in Nanome
Home-page: https://github.com/nanome-ai/plugin-vault
Author: Nanome
Author-email: hello@nanome.ai
License: MIT
Keywords: virtual-reality,chemistry,python,api,plugin
Platform: any
Classifier: Development Status :: 3 - Alpha
Classifier: Intended Audience :: Science/Research
Classifier: Topic :: Scientific/Engineering :: Chemistry
Classifier: License :: OSI Approved :: MIT License
Classifier: Programming Language :: Python :: 3.6
Classifier: Programming Language :: Python :: 3.7
Classifier: Programming Language :: Python :: 3.8
Requires-Dist: nanome
Requires-Dist: pycryptodome
Requires-Dist: requests
